supertelbot/__init__.py
supertelbot/bots/__init__.py
supertelbot/bots/image_generation.py
supertelbot/bots/nmap.py
supertelbot/bots/passwords.json
supertelbot/bots/passwords.py
supertelbot/bots/spider.py
supertelbot/bots/weather.py
supertelbot/bots/__pycache__/__init__.cpython-39.pyc
supertelbot/bots/__pycache__/image_generation.cpython-39.pyc
supertelbot/bots/__pycache__/nmap.cpython-39.pyc
supertelbot/bots/__pycache__/passwords.cpython-39.pyc
supertelbot/bots/__pycache__/spider.cpython-39.pyc
supertelbot/bots/__pycache__/weather.cpython-39.pyc
supertelbot/core/__init__.py
supertelbot/core/api.py
supertelbot/core/exceptions.py
supertelbot/core/keyboards.py
supertelbot/core/manager.py
supertelbot/core/models.py
supertelbot/core/utils.py
supertelbot/core/workers.py
supertelbot/core/__pycache__/__init__.cpython-39.pyc
supertelbot/core/__pycache__/api.cpython-39.pyc
supertelbot/core/__pycache__/exceptions.cpython-39.pyc
supertelbot/core/__pycache__/keyboards.cpython-39.pyc
supertelbot/core/__pycache__/manager.cpython-39.pyc
supertelbot/core/__pycache__/models.cpython-39.pyc
supertelbot/core/__pycache__/utils.cpython-39.pyc
supertelbot/core/__pycache__/workers.cpython-39.pyc
supertelbot/modules/__init__.py
supertelbot/modules/image_generation.py
supertelbot/modules/nmap_scanner.py
supertelbot/modules/passwords.py
supertelbot/modules/person.py
supertelbot/modules/shodan.py
supertelbot/modules/spider.py
supertelbot/modules/weather.py
supertelbot/modules/__pycache__/__init__.cpython-39.pyc
supertelbot/modules/__pycache__/image_generation.cpython-39.pyc
supertelbot/modules/__pycache__/nmap_scanner.cpython-39.pyc
supertelbot/modules/__pycache__/passwords.cpython-39.pyc
supertelbot/modules/__pycache__/spider.cpython-39.pyc
supertelbot/modules/__pycache__/weather.cpython-39.pyc
SuperTelBot-0.1.15.dist-info/METADATA
SuperTelBot-0.1.15.dist-info/WHEEL
SuperTelBot-0.1.15.dist-info/top_level.txt
SuperTelBot-0.1.15.dist-info/RECORD
